infra_generator/__init__.py
infra_generator/chroma_manager.py
infra_generator/config.yaml
infra_generator/embedder.py
infra_generator/gitingest_exp.py
infra_generator/infra_agent.py
infra_generator/infra_generator.py
infra_generator/main.py
infra_generator/prompt_templates.py
infra_generator/query_handler.py
infra_generator/retriever.py
infra_generator/setup_ollama.py
infra_generator/utils.py
infra_generator/tools/git_tools.py
infra_generator/tools/infra_tools.py
local_ai_infra_generation-1.1.1.dist-info/licenses/LICENSE
local_ai_infra_generation-1.1.1.dist-info/METADATA
local_ai_infra_generation-1.1.1.dist-info/WHEEL
local_ai_infra_generation-1.1.1.dist-info/entry_points.txt
local_ai_infra_generation-1.1.1.dist-info/top_level.txt
local_ai_infra_generation-1.1.1.dist-info/RECORD
