Metadata-Version: 2.4
Name: local-ai-infra-generation
Version: 1.1.1
Summary: A tool to generate infrastructure files (Dockerfile, etc.) for codebases using local LLMs.
Author-email: Lishuai Jing <lishuai@syncable.dev>
Project-URL: Homepage, https://github.com/LishuaiJing3/local-AI-infra-generation
Project-URL: Bug Tracker, https://github.com/LishuaiJing3/local-AI-infra-generation/issues
Classifier: Programming Language :: Python :: 3
Classifier: License :: OSI Approved :: MIT License
Classifier: Operating System :: OS Independent
Classifier: Development Status :: 3 - Alpha
Classifier: Topic :: Software Development :: Code Generators
Classifier: Topic :: System :: Systems Administration
Requires-Python: >=3.11
License-File: LICENSE
Requires-Dist: chromadb
Requires-Dist: langchain
Requires-Dist: langchain-community
Requires-Dist: pyyaml
Requires-Dist: requests
Requires-Dist: tqdm
Requires-Dist: tree-sitter-languages
Requires-Dist: typing-extensions
Requires-Dist: langchain-ollama
Requires-Dist: uv
Requires-Dist: gitingest
Provides-Extra: dev
Requires-Dist: python-semantic-release; extra == "dev"
Requires-Dist: pytest; extra == "dev"
Requires-Dist: build; extra == "dev"
Dynamic: license-file
